equipment_sequence/__init__.py
equipment_sequence/crrc_package/__init__.py
equipment_sequence/crrc_package/package_print/__init__.py
equipment_sequence/crrc_package/package_print/database_table_model.py
equipment_sequence/crrc_package/package_print/package_print.json
equipment_sequence/crrc_package/package_print/package_print.py
equipment_sequence/crrc_package/plastic_print/__init__.py
equipment_sequence/crrc_package/plastic_print/database_table_model.py
equipment_sequence/crrc_package/plastic_print/plastic_print.json
equipment_sequence/crrc_package/plastic_print/plastic_print.py
equipment_sequence/crrc_package/plastic_print/zhong_che_package.xlsx
equipment_sequence/crrc_package/uploading/__init__.py
equipment_sequence/crrc_package/uploading/database_table_model.py
equipment_sequence/crrc_package/uploading/uploading.json
equipment_sequence/crrc_package/uploading/uploading.py
equipment_sequence/crrc_package/uploading/uploading_official.json
equipment_sequence/crrc_package/uploading/uploading_official.py
equipment_sequence/crrc_package/zhong_che_package.xlsx
equipment_sequence/hua_run_wei/__init__.py
equipment_sequence/hua_run_wei/hua_run_wei.json
equipment_sequence/hua_run_wei/hua_run_wei.py
equipment_sequence/hua_run_wei/hua_run_wei_manual.xlsx
equipment_sequence/infineon/__init__.py
equipment_sequence/infineon/infineon.json
equipment_sequence/infineon/infineon.py
equipment_sequence/infineon/infineon_manual_20250616.xlsx
equipment_sequence/lin_zhong/__init__.py
equipment_sequence/lin_zhong/system_solder/__init__.py
equipment_sequence/lin_zhong/system_solder/system_solder.json
equipment_sequence/lin_zhong/system_solder/system_solder.py
equipment_sequence/lin_zhong/system_solder/system_solder_manual_20250616_new.xlsx
equipment_sequence/lin_zhong/system_solder/table_models.py
equipment_sequence/main.py
equipment_sequence/rui_di_wei/__init__.py
equipment_sequence/rui_di_wei/cutting/__init__.py
equipment_sequence/rui_di_wei/cutting/cutting.json
equipment_sequence-1.4.0.dist-info/METADATA
equipment_sequence-1.4.0.dist-info/WHEEL
equipment_sequence-1.4.0.dist-info/RECORD
