Metadata-Version: 2.3
Name: equipment-sequence
Version: 1.4.0
Summary: 设备业务逻辑
Author: LiuWei
Author-email: 183074632@qq.com
Requires-Python: >=3.11,<3.13
Classifier: Programming Language :: Python :: 3
Classifier: Programming Language :: Python :: 3.11
Classifier: Programming Language :: Python :: 3.12
Requires-Dist: passive-equipment (>=2.6.0,<3.0.0)
